{
  "type": "bundle",
  "id": "bundle--7ea38a8c-6404-4f9f-b85e-5d97873c5668",
  "spec_version": "2.0",
  "x_usa_gov_banner_marking_ref": "marking-definition--d3996c0d-f816-4906-b651-a8386b9760f9", 
  "objects": [
  {
        "type": "marking-definition",
        "id": "marking-definition--d14a79b3-53a0-4f84-90a5-7073f9be8e50",
        "created": "2018-08-01T00:00:00Z",
        "definition_type": "x-isa-acs-3-0",
        "definition": {
            "sep_version": 1,
            "identifier": "isa:guide.19001.ACS3-d3664e7d-4a74-44d3-935e-cc13a661a710",
            "name": "default_object_marking",
            "create_date_time": "2016-06-27T14:10:26.723Z",
            "responsible_entity_custodian": "USA.NSA",
            "responsible_entity_originator": "USA.NSA",
            "authority_reference": "urn:isa:authority:CFR2013_32_2_236",
            "derivative_classification": {
                "classified_by": "Available-On-Request",
                "derived_from": "Orig-Doc"
            },
            "declassification": {
                "declass_date": "2020-02-20T00:00:00Z"
            },
            "public_release": {
               "releasable_to_public": false
            },
            "control_set": {
                "classification": "TS//SI//NF",
                "sci_controls": ["SI"],
                "formal_determination": ["AIS"],
                "logical_authority_category": ["LAC12345"],
                "sensitivity": ["NTOC_DHS_ECYBER_SVC_SHARE.NSA.NSA"],
                "permitted_organizations": ["USA.NSA", "USA.DHS"]
            }
    },
    {
        "type": "marking-definition",
        "id": "marking-definition--4c3d3dec-1511-439a-a7ae-c734c908bca1",
        "created": "2018-08-01T00:00:00Z",
        "definition_type": "x-isa-acs-3-0", 
        "definition": {
            "sep_version": 1,
            "identifier": "isa:guide.19001.ACS4-bc9034f8-c732-5328-b9df-d9d72aaeaaaa",
            "name": "some_secret_marking",
            "create_date_time": "2016-06-27T14:10:26.723Z",
            "responsible_entity_custodian": "USA.NSA",
            "responsible_entity_originator": "USA.NSA",
            "authority_reference": "urn:isa:authority:CFR2013_32_2_236", 
            "derivative_classification": {
                "classified_by": "Available-On-Request",
                "derived_from": "Orig-Doc"
            },
            "declassification": {
                "declass_date": "2020-02-20T00:00:00Z"
            },
            "public_release": {
               "releasable_to_public": false
            },
            "control_set": {
            	"classification": "TS",
            	"sci_controls": ["SI"],
            	"logical_authority_category": ["LAC12345"],
            	"formal_determination": ["AIS"],
            	"sensitivity": ["NTOC_DHS_ECYBER_SVC_SHARE.NSA.NSA"],
            	"permitted_nationalities": ["USA", "AUS", "CAN", "GBR", "NZL"],
            	"permitted_organizations": ["USA.NSA", "USA.DHS"]
            }
        }
    },
    {
        "type": "marking-definition",
        "id": "marking-definition--d3996c0d-f816-4906-b651-a8386b9760f9",
        "created": "2018-08-01T00:00:00Z",
        "definition_type": "x-isa-acs-3-0", 
        "definition": {
            "sep_version": 1,
            "identifier": "isa:guide.19001.ACS4-bc9034f8-c732-5328-b9df-d9d72aae480b",
            "name": "banner-marking",
            "create_date_time": "2016-06-27T14:10:26.723Z",
            "responsible_entity_custodian": "USA.NSA",
            "responsible_entity_originator": "USA.NSA",
            "authority_reference": "urn:isa:authority:CFR2013_32_2_236", 
            "derivative_classification": {
                "classified_by": "Available-On-Request",
                "derived_from": "Orig-Doc"
            },
            "declassification": {
               "declass_date": "2020-02-20T00:00:00Z"
            },
            "public_release": {
               "releasable_to_public": false
            },
            "control_set": {
               "capco_classification": "TS//SI//NF",
               "logical_authority_category": ["LAC12345"],
               "community_of_interest ": ["NTOC_DHS_ECYBER_SVC_SHARE.NSA.NSA"],
               "organization": ["USA.NSA", "USA.DHS"]
            },
            "other_determination": [
                "AIS", 
                "INFORMATION-DIRECTLY-RELATED-TO-CYBERSECURITY-THREAT"
            ],
            "terms_of_use": ["May be used for network defense for CISA uses. Anonymous access is not allowed. May be further shared with…."]
        }
    },
    {
        "type": "marking-definition",
        "id": "marking-definition--35149430-7912-4e6f-8223-baec65c2c744",
        "created": "2018-08-01T00:00:00Z",
        "definition_type": "x-isa-acs-3-0", 
        "definition": {
            "sep_version": 1,
            "identifier": "isa:guide.19001.ACS4-bc9034f8-c732-5328-b9df-d9d72aae4bbb",
            "name": "some_top_secret_marking",
            "create_date_time": "2016-06-27T14:10:26.723Z",
            "responsible_entity_custodian": "USA.NSA",
            "responsible_entity_originator": "USA.NSA",
            "authority_reference": "urn:isa:authority:CFR2013_32_2_236",
            "derivative_classification": {
                "classified_by": "Available-On-Request",
                "derived_from": "Orig-Doc"
            },
            "declassification": {
                "declass_date": "2020-02-20T00:00:00Z"
            },
            "public_release": {
               "releasable_to_public": false
            },
            "control_set": {
                "capco_classification": "TS//NF",
                "logical_authority_category": ["LAC12345"],
                "community_of_interest ": ["NTOC_DHS_ECYBER_SVC_SHARE.NSA.NSA"],
                "organization": ["USA.NSA", "USA.DHS"]
            },
            "other_dissemination": [
                "AIS", 
                "INFORMATION-DIRECTLY-RELATED-TO-CYBERSECURITY-THREAT"
            ], 
            "terms_of_use": ["May be used for network defense for CISA uses. Anonymous access is not allowed. May be further shared with…."]
         }
     },
     {
        "type": "marking-definition",
        "id": "marking-definition--31edda00-1627-43cc-b6d5-40721ea47068",
        "created": "2018-08-01T00:00:00Z",
        "definition_type": "x-isa-acs-3-0", 
        "definition": {
            "sep_version": 1,
            "identifier": "isa:guide.19001.ACS4-bc9034f8-c732-5328-b9df-d9d72aae4ccc",
            "name": "some_unclassified_marking",
            "create_date_time": "2016-06-27T14:10:26.723Z",
            "responsible_entity_custodian": "USA.NSA",
            "responsible_entity_originator": "USA.NSA",
            "authority_reference": "urn:isa:authority:CFR2013_32_2_236",
            "public_release": {
               "releasable_to_public": true,
               "released_by": "DHS Public Relations Office",
               "released_on": "2018-07-20T00:00:00Z"
            },
            "control_set": {
                "capco_classification": "U//FOUO",
                "organization": ["USA.NSA", "USA.DHS"]
            },
            "other_determination": ["AIS", "INFORMATION-DIRECTLY-RELATED-TO-CYBERSECURITY-THREAT"],
            "terms_of_use": ["May be used for network defense for CISA uses. Anonymous access is not allowed. May be further shared with…."]
        }
   },
   {
        "type": "indicator",
        "id": "indicator--UUID-I1",
        "created": "2014-05-08T09:00:00.000000Z",
        "modified": "2014-05-08T09:00:00.000000Z",
        "labels": ["malicious-activity"],
        "name": "Bad IP address",
        "description": "This is a Bad IP address",
        "pattern": "ipv4addr-object:value = '10.0.0.0'",
        "valid_from": "2014-05-08T09:00:00.000000Z", 
        "object_marking_refs": ["marking-definition--d14a79b3-53a0-4f84-90a5-7073f9be8e50"], 
        "granular_markings": [
            {
                "marking_ref": "marking-definition--31edda00-1627-43cc-b6d5-40721ea47068",
                "selectors": ["type", "id", "created", "modified", "labels", "valid_from"]
            },
            {
                "marking_ref": "marking-definition--35149430-7912-4e6f-8223-baec65c2c744",
                "selectors": ["description", "name"]
            },
            {
                "marking_ref": "marking-definition--4c3d3dec-1511-439a-a7ae-c734c908bca1",
                "selectors": ["pattern"]
            }
        ]  
   }]
}
